LICENSE.txt
MANIFEST.in
README.md
README.rst
requirements.txt
setup.py
spruned/__init__.py
spruned/app.py
spruned/builder.py
spruned/main.py
spruned/settings.py
spruned.egg-info/PKG-INFO
spruned.egg-info/SOURCES.txt
spruned.egg-info/dependency_links.txt
spruned.egg-info/entry_points.txt
spruned.egg-info/requires.txt
spruned.egg-info/top_level.txt
spruned/application/__init__.py
spruned/application/abstracts.py
spruned/application/cache.py
spruned/application/context.py
spruned/application/database.py
spruned/application/exceptions.py
spruned/application/jsonrpc_server.py
spruned/application/logging_factory.py
spruned/application/mempool_observer.py
spruned/application/spruned_vo_service.py
spruned/application/tools.py
spruned/application/migrations/__init__.py
spruned/application/migrations/migration_1.py
spruned/application/migrations/migration_2.py
spruned/application/networks/__init__.py
spruned/application/networks/bitcoin.py
spruned/application/utils/__init__.py
spruned/application/utils/jsonrpc_client.py
spruned/daemon/__init__.py
spruned/daemon/abstracts.py
spruned/daemon/connection_base_impl.py
spruned/daemon/connectionpool_base_impl.py
spruned/daemon/exceptions.py
spruned/daemon/zeromq.py
spruned/daemon/bitcoin_p2p/__init__.py
spruned/daemon/bitcoin_p2p/p2p_connection.py
spruned/daemon/bitcoin_p2p/p2p_interface.py
spruned/daemon/bitcoin_p2p/p2p_peers.json
spruned/daemon/bitcoin_p2p/utils.py
spruned/daemon/electrod/__init__.py
spruned/daemon/electrod/electrod_connection.py
spruned/daemon/electrod/electrod_fee_estimation.py
spruned/daemon/electrod/electrod_interface.py
spruned/daemon/electrod/electrum_servers.json
spruned/daemon/tasks/__init__.py
spruned/daemon/tasks/blocks_reactor.py
spruned/daemon/tasks/headers_reactor.py
spruned/dependencies/__init__.py
spruned/dependencies/connectrum.py
spruned/dependencies/pybitcointools.py
spruned/dependencies/pycoinnet/MappingQueue.py
spruned/dependencies/pycoinnet/Peer.py
spruned/dependencies/pycoinnet/PeerEvent.py
spruned/dependencies/pycoinnet/__init__.py
spruned/dependencies/pycoinnet/dnsbootstrap.py
spruned/dependencies/pycoinnet/inv_batcher.py
spruned/dependencies/pycoinnet/inv_fetcher.py
