Metadata-Version: 1.2
Name: spruned
Version: 0.0.10
Summary: Bitcoin Lightweight Pseudonode
Home-page: https://github.com/gdassori/spruned/
Author: Guido Dassori
Author-email: guido.dassori@gmail.com
License: MIT
Platform: UNKNOWN
Classifier: Development Status :: 3 - Alpha
Classifier: License :: OSI Approved :: MIT License
Classifier: Programming Language :: Python :: 3.5
Classifier: Programming Language :: Python :: 3.6
Requires-Python: >=3.5.2
